Lab3/part1/traffic_light_controller1.sv
// traffic light controller
// CSE140L 3-street, 12-state version
// inserts all-red after each yellow
// uses enumerated variables for states and for red-yellow-green
// 5 after traffic, 10 max cycles for green after conflict
// starter (shell) -- you need to complete the always_comb logic
import light_package ::*;           // defines red, yellow, green

// same as Harris & Harris 4-state, but we have added two all-reds
module traffic_light_controller1(
  input         clk, reset, 
                ew_str_sensor, ew_left_sensor, ns_sensor,  // traffic sensors, east-west straight, east-west left, north-south 
  output colors ew_str_light, ew_left_light, ns_light);    // traffic lights, east-west straight, east-west left, north-south

// HRR = red-red following YRR; RRH = red-red following RRY;
// ZRR = 2nd cycle yellow, follows YRR, etc. 
  typedef enum {GRR, YRR, ZRR, HRR, RGR, RYR, RZR, RHR, RRG, RRY, RRZ, RRH} tlc_states;  
  tlc_states    present_state, next_state;
  integer ctr5, next_ctr5,       //  5 sec timeout when my traffic goes away
          ctr10, next_ctr10;     // 10 sec limit when other traffic presents

// sequential part of our state machine (register between C1 and C2 in Harris & Harris Moore machine diagram
// combinational part will reset or increment the counters and figure out the next_state
  always_ff @(posedge clk)
    if(reset) begin
	  present_state <= RRH;
      ctr5          <= 0;
      ctr10         <= 0;
    end  
	else begin
	  present_state <= next_state;
      ctr5          <= next_ctr5;
      ctr10         <= next_ctr10;
    end  

// combinational part of state machine ("C1" block in the Harris & Harris Moore machine diagram)
// default needed because only 6 of 8 possible states are defined/used
  always_comb begin
    next_state = RRH;            // default to reset state
    next_ctr5  = 0; 	         // default to clearing counters
    next_ctr10 = 0;
    case(present_state)
/* ************* Fill in the case statements ************** */
  // Green
	  GRR: begin 
        if ((ew_str_sensor == 0) || (ctr5 > 0))
        	next_ctr5 = ctr5 + 1;
        
        if ((ew_left_sensor == 1) || (ns_sensor == 1) || (ctr10 > 0)) 
          next_ctr10 = ctr10 + 1;
        
        if (ctr5 >= 4 || ctr10 >= 9) next_state = YRR;
        else next_state = GRR;
      end
	  RGR: begin 
        if ((ew_left_sensor == 0) || (ctr5 > 0))
        	next_ctr5 = ctr5 + 1;
        
        if ((ew_str_sensor == 1) || (ns_sensor == 1) || (ctr10 > 0)) 
          next_ctr10 = ctr10 + 1;
        
        if (ctr5 >= 4 || ctr10 >= 9) next_state = RYR;
        else next_state = RGR;
      end
	  RRG: begin 
        if ((ns_sensor == 0) || (ctr5 > 0))
        	next_ctr5 = ctr5 + 1;
        
        if ((ew_left_sensor == 1) || (ew_str_sensor == 1) || (ctr10 > 0)) 
          next_ctr10 = ctr10 + 1;
        
        if (ctr5 >= 4 || ctr10 >= 9) next_state = RRY;
        else next_state = RRG;
      end
      
      // red 
      HRR: begin
        if (ew_left_sensor)
          next_state = RGR;
        else if (ns_sensor)
          next_state = RRG;
        else if (ew_str_sensor)
          next_state = GRR;
        else 
			   next_state = present_state;
      end
      RHR: begin
        if (ns_sensor)
          next_state = RRG;
        else if (ew_str_sensor)
          next_state = GRR;
        else if (ew_left_sensor)
          next_state = RGR;
        else 
			    next_state = present_state;
      end
      RRH: begin
        if (ew_str_sensor)
          next_state = GRR;
        else if (ew_left_sensor)
          next_state = RGR;
        else if (ns_sensor)
          next_state = RRG;
        else 
			    next_state = present_state;
      end
      
      // yellow 
      YRR: next_state = ZRR;
      ZRR: next_state = HRR;
      RYR: next_state = RZR;
      RZR: next_state = RHR;
      RRY: next_state = RRZ;
      RRZ: next_state = RRH;
    endcase
  end

// combination output driver  ("C2" block in the Harris & Harris Moore machine diagram)
  always_comb begin
    ew_str_light  = red;                // cover all red plus undefined cases
	ew_left_light = red;
	ns_light      = red;
    case(present_state)      // Moore machine
      GRR:     ew_str_light  = green;
	  YRR,ZRR: ew_str_light  = yellow;  // my dual yellow states -- brute force way to make yellow last 2 cycles
	  RGR:     ew_left_light = green;
	  RYR,RZR: ew_left_light = yellow;
	  RRG:     ns_light      = green;
	  RRY,RRZ: ns_light      = yellow;
    endcase
  end

endmodule

Lab3/part1/lab3_part1_tb.sv
// test bench for Lab 3 part 1  -- write to file version
// CSE140L   
// expanded version -- try the simpler traffic_tb first if
//  you do not pass this one
import light_package::*;   // maps 2'b00, 01, 10 to red, yellow, green
                           //typedef enum logic[1:0] {red,yellow,green} color;
//typedef enum logic[1:0] {red,yellow,green} colors;
module lab3_part1_tb;

bit    clk;					   // bit is like logic, but self-initializes to 0, no x or z allowed
bit    reset = 1'b1;		   // should put your design in all-red
bit    ew_left_sensor,         // left-turning traffic from e-w street to n-s street
	   ew_str_sensor,          // straight thru traffic on e-w street
	   ns_sensor;              // left turning or through traffic on n-s street
colors ew_left_light,          // left arrow turn from e-w onto n-s
	   ew_str_light,	       // straight ahead e-w
	   ns_light;	           // n-s (no left/thru differentiation)
//colors ew_left_light1,         // left arrow e-w turn onto n-s
//	   ew_str_light1,	       // straight ahead e-w
//	   ns_light1;	           // n-s (no left/thru differentiation)

// your controller goes here
// input ports = logics above
// output ports = colors (each 2 bits wide)
traffic_light_controller1 dut(.clk(clk),
       .reset(reset),
       .ew_str_sensor(ew_str_sensor), 
       .ew_left_sensor(ew_left_sensor), 
       .ns_sensor(ns_sensor),
       .ew_str_light(ew_str_light),
       .ew_left_light(ew_left_light),
       .ns_light);

int fi;
int test_cnt;          // lets testbench track tests
  initial begin          // temporary emergency brake -- comment out once you get past line 54 wait(ew_str_light == green);
  #20000ns $stop; 
end  
initial begin
  $dumpfile("dump.vcd");
  $dumpvars;
  //fi = $fopen("lab3_part1_results.txt","w");
  $fdisplay(fi,"t   t   t   e   e   n");	   // header for y, g status display
  $fdisplay(fi,"s   l   n   w   w   s");
  $fdisplay(fi,"            s   l    ");
  $fmonitor(fi, "Test Case: %d", test_cnt);
  #20ns reset    = 1'b0;
  #10ns;
// Test EW_LEFT to EW_STR without more traffic
  test_cnt++                  ;
  fork
    begin
      #10ns ew_str_sensor  =  1'b1;
      wait (ew_str_light == green);
	  #25ns ew_str_sensor  =  1'b0;
	end
    begin
            ew_left_sensor =  1'b1 ;
      wait (ew_left_light == green);
      #15ns ew_left_sensor =  1'b0 ;
	end
  join
  #200ns;

// Now set traffic at NS. Green NS lasts past sensor falling
  test_cnt++              ;
        ns_sensor = 1'b1  ;
  wait (ns_light == green);
  #35ns ns_sensor = 1'b0  ;
  #200ns;

// Check NS again, but hold for more than 5 cycles.
//   NS should cycle green-yellow-red when side traffic appears
  test_cnt++;
  ns_sensor              = 1'b1;
  #100ns  ew_left_sensor = 1'b1;
  #200ns ns_sensor       = 1'b0;
  #10ns ew_left_sensor  = 1'b0;
  #200ns;

// All three sensors become 1 at once.
//  EW_STR should come first, then LEFT, then NS
  test_cnt++;
  ew_left_sensor = 1'b1;
  ew_str_sensor  = 1'b1;
  ns_sensor      = 1'b1;
  #1000ns;
  ew_left_sensor = 1'b0;
  #200ns;
  ew_str_sensor  = 1'b0;
  ns_sensor      = 1'b0;
  #200ns;

// All
  test_cnt++;
  $stop;
end

always begin
  #3ns;
// print active sensors into result file
  if(ew_str_sensor)
    $fwrite(fi,"es  ");
  else
    $fwrite(fi,"    ");
  if(ew_left_sensor)
    $fwrite(fi,"el  ");
  else
    $fwrite(fi,"    ");
  if(ns_sensor)
    $fwrite(fi,"ns  ");
  else
    $fwrite(fi,"    ");
// print yellow and green states into result file
// red states will be denoted by blank spaces, for easier reading
  case({ew_str_light,ew_left_light,ns_light})
    {red,red,red}   : $fdisplay(fi,"             %t",$time);
	{yellow,red,red}: $fdisplay(fi,"sy           %t",$time);
	{green,red,red} : $fdisplay(fi,"sg           %t",$time);
	{red,yellow,red}: $fdisplay(fi,"    ly       %t",$time);
	{red,green,red} : $fdisplay(fi,"    lg       %t",$time);
	{red,red,yellow}: $fdisplay(fi,"        ny   %t",$time);
	{red,red,green} : $fdisplay(fi,"        ng   %t",$time);
	default    : $fdisplay(fi,"***ERROR**   %t",$time);
  endcase
  #2ns clk = 1'b1;
  #5ns clk = 1'b0; 
end

endmodule

Lab3/part1/dump.vcd
$date
	Tue Nov 14 16:45:42 2023
$end
$version
	ModelSim Version 10.5b
$end
$timescale
	1ps
$end

$scope module lab3_part1_tb $end
$var reg 1 ! clk $end
$var reg 1 " reset $end
$var reg 1 # ew_left_sensor $end
$var reg 1 $ ew_str_sensor $end
$var reg 1 % ns_sensor $end
$var reg 2 & ew_left_light [1:0] $end
$var reg 2 ' ew_str_light [1:0] $end
$var reg 2 ( ns_light [1:0] $end
$var integer 32 ) fi $end
$var integer 32 * test_cnt $end

$scope module dut $end
$var wire 1 + clk $end
$var wire 1 , reset $end
$var wire 1 - ew_str_sensor $end
$var wire 1 . ew_left_sensor $end
$var wire 1 / ns_sensor $end
$var reg 2 0 ew_str_light [1:0] $end
$var reg 2 1 ew_left_light [1:0] $end
$var reg 2 2 ns_light [1:0] $end
$var integer 32 3 present_state $end
$var integer 32 4 next_state $end
$var integer 32 5 ctr5 $end
$var integer 32 6 next_ctr5 $end
$var integer 32 7 ctr10 $end
$var integer 32 8 next_ctr10 $end
$upscope $end
$upscope $end

$scope begin light_package $end
$upscope $end

$scope begin lab3_part1_tb_sv_unit $end
$upscope $end

$scope begin std $end
$upscope $end

$scope begin traffic_light_controller1_sv_unit $end
$upscope $end
$enddefinitions $end
#0
$dumpvars
0!
1"
0#
0$
0%
b0 &
b10 '
b0 (
b10 0
b0 1
b0 2
b0 3
b0 4
bx 5
bx 6
bx 7
b0 8
b10000000000000000000000000000011 )
b0 *
0+
1,
0-
0.
0/
$end
#5000
1!
1+
b1011 3
b0 5
b0 7
b1011 4
b0 6
b0 0
b0 '
#10000
0!
0+
#15000
1!
1+
#20000
0"
0!
0,
0+
#25000
1!
1+
#30000
b1 *
1#
0!
1.
0+
b100 4
#35000
1!
1+
b100 3
b1011 4
b100 4
b10 1
b10 &
#40000
1$
0!
1-
0+
b1011 4
b1 8
b100 4
#45000
1!
1+
b1 7
b1011 4
b0 8
b10 8
b100 4
#50000
0#
0!
0.
0+
b1011 4
b0 8
b1 6
b10 8
b100 4
#55000
1!
1+
b1 5
b10 7
b1011 4
b0 6
b0 8
b10 6
b11 8
b100 4
#60000
0!
0+
#65000
1!
1+
b10 5
b11 7
b1011 4
b0 6
b0 8
b11 6
b100 8
b100 4
#70000
0!
0+
#75000
1!
1+
b11 5
b100 7
b1011 4
b0 6
b0 8
b100 6
b101 8
b100 4
#80000
0!
0+
#85000
1!
1+
b100 5
b101 7
b1011 4
b0 6
b0 8
b101 6
b110 8
b101 4
#90000
0!
0+
#95000
1!
1+
b101 3
b101 5
b110 7
b1011 4
b0 6
b0 8
b110 4
b0 1
b1 1
b1 &
#100000
0!
0+
#105000
1!
1+
b110 3
b0 5
b0 7
b1011 4
b111 4
b0 1
b1 1
#110000
0!
0+
#115000
1!
1+
b111 3
b1011 4
b0 4
b0 1
b0 &
#120000
0!
0+
#125000
1!
1+
b0 3
b1011 4
b0 4
b10 0
b10 '
#130000
0!
0+
#135000
1!
1+
#140000
0!
0+
#145000
1!
1+
#150000
0$
0!
0-
0+
b1011 4
b1 6
b0 4
#155000
1!
1+
b1 5
b1011 4
b0 6
b10 6
b0 4
#160000
0!
0+
#165000
1!
1+
b10 5
b1011 4
b0 6
b11 6
b0 4
#170000
0!
0+
#175000
1!
1+
b11 5
b1011 4
b0 6
b100 6
b0 4
#180000
0!
0+
#185000
1!
1+
b100 5
b1011 4
b0 6
b101 6
b1 4
#190000
0!
0+
#195000
1!
1+
b1 3
b101 5
b1011 4
b0 6
b10 4
b0 0
b1 0
b1 '
#200000
0!
0+
#205000
1!
1+
b10 3
b0 5
b1011 4
b11 4
b0 0
b1 0
#210000
0!
0+
#215000
1!
1+
b11 3
b1011 4
b0 0
b0 '
#220000
0!
0+
#225000
1!
1+
b1011 3
#230000
0!
0+
#235000
1!
1+
#240000
0!
0+
#245000
1!
1+
#250000
0!
0+
#255000
1!
1+
#260000
0!
0+
#265000
1!
1+
#270000
0!
0+
#275000
1!
1+
#280000
0!
0+
#285000
1!
1+
#290000
0!
0+
#295000
1!
1+
#300000
0!
0+
#305000
1!
1+
#310000
0!
0+
#315000
1!
1+
#320000
0!
0+
#325000
1!
1+
#330000
0!
0+
#335000
1!
1+
#340000
0!
0+
#345000
1!
1+
#350000
b10 *
1%
0!
1/
0+
b1000 4
#355000
1!
1+
b1000 3
b1011 4
b1000 4
b10 2
b10 (
#360000
0!
0+
#365000
1!
1+
#370000
0!
0+
#375000
1!
1+
#380000
0!
0+
#385000
1!
1+
#390000
0%
0!
0/
0+
b1011 4
b1 6
b1000 4
#395000
1!
1+
b1 5
b1011 4
b0 6
b10 6
b1000 4
#400000
0!
0+
#405000
1!
1+
b10 5
b1011 4
b0 6
b11 6
b1000 4
#410000
0!
0+
#415000
1!
1+
b11 5
b1011 4
b0 6
b100 6
b1000 4
#420000
0!
0+
#425000
1!
1+
b100 5
b1011 4
b0 6
b101 6
b1001 4
#430000
0!
0+
#435000
1!
1+
b1001 3
b101 5
b1011 4
b0 6
b1010 4
b0 2
b1 2
b1 (
#440000
0!
0+
#445000
1!
1+
b1010 3
b0 5
b1011 4
b0 2
b1 2
#450000
0!
0+
#455000
1!
1+
b1011 3
b0 2
b0 (
#460000
0!
0+
#465000
1!
1+
#470000
0!
0+
#475000
1!
1+
#480000
0!
0+
#485000
1!
1+
#490000
0!
0+
#495000
1!
1+
#500000
0!
0+
#505000
1!
1+
#510000
0!
0+
#515000
1!
1+
#520000
0!
0+
#525000
1!
1+
#530000
0!
0+
#535000
1!
1+
#540000
0!
0+
#545000
1!
1+
#550000
0!
0+
#555000
1!
1+
#560000
0!
0+
#565000
1!
1+
#570000
0!
0+
#575000
1!
1+
#580000
0!
0+
#585000
1!
1+
#590000
b11 *
1%
0!
1/
0+
b1000 4
#595000
1!
1+
b1000 3
b1011 4
b1000 4
b10 2
b10 (
#600000
0!
0+
#605000
1!
1+
#610000
0!
0+
#615000
1!
1+
#620000
0!
0+
#625000
1!
1+
#630000
0!
0+
#635000
1!
1+
#640000
0!
0+
#645000
1!
1+
#650000
0!
0+
#655000
1!
1+
#660000
0!
0+
#665000
1!
1+
#670000
0!
0+
#675000
1!
1+
#680000
0!
0+
#685000
1!
1+
#690000
1#
0!
1.
0+
b1011 4
b1 8
b1000 4
#695000
1!
1+
b1 7
b1011 4
b0 8
b10 8
b1000 4
#700000
0!
0+
#705000
1!
1+
b10 7
b1011 4
b0 8
b11 8
b1000 4
#710000
0!
0+
#715000
1!
1+
b11 7
b1011 4
b0 8
b100 8
b1000 4
#720000
0!
0+
#725000
1!
1+
b100 7
b1011 4
b0 8
b101 8
b1000 4
#730000
0!
0+
#735000
1!
1+
b101 7
b1011 4
b0 8
b110 8
b1000 4
#740000
0!
0+
#745000
1!
1+
b110 7
b1011 4
b0 8
b111 8
b1000 4
#750000
0!
0+
#755000
1!
1+
b111 7
b1011 4
b0 8
b1000 8
b1000 4
#760000
0!
0+
#765000
1!
1+
b1000 7
b1011 4
b0 8
b1001 8
b1000 4
#770000
0!
0+
#775000
1!
1+
b1001 7
b1011 4
b0 8
b1010 8
b1001 4
#780000
0!
0+
#785000
1!
1+
b1001 3
b1010 7
b1011 4
b0 8
b1010 4
b0 2
b1 2
b1 (
#790000
0!
0+
#795000
1!
1+
b1010 3
b0 7
b1011 4
b0 2
b1 2
#800000
0!
0+
#805000
1!
1+
b1011 3
b100 4
b0 2
b0 (
#810000
0!
0+
#815000
1!
1+
b100 3
b1011 4
b1 8
b100 4
b10 1
b10 &
#820000
0!
0+
#825000
1!
1+
b1 7
b1011 4
b0 8
b10 8
b100 4
#830000
0!
0+
#835000
1!
1+
b10 7
b1011 4
b0 8
b11 8
b100 4
#840000
0!
0+
#845000
1!
1+
b11 7
b1011 4
b0 8
b100 8
b100 4
#850000
0!
0+
#855000
1!
1+
b100 7
b1011 4
b0 8
b101 8
b100 4
#860000
0!
0+
#865000
1!
1+
b101 7
b1011 4
b0 8
b110 8
b100 4
#870000
0!
0+
#875000
1!
1+
b110 7
b1011 4
b0 8
b111 8
b100 4
#880000
0!
0+
#885000
1!
1+
b111 7
b1011 4
b0 8
b1000 8
b100 4
#890000
0%
0!
0/
0+
b1011 4
b0 8
b1000 8
b100 4
#895000
1!
1+
b1000 7
b1011 4
b0 8
b1001 8
b100 4
#900000
0#
0!
0.
0+
b1011 4
b0 8
b1 6
b1001 8
b100 4
#905000
1!
1+
b1 5
b1001 7
b1011 4
b0 6
b0 8
b10 6
b1010 8
b101 4
#910000
0!
0+
#915000
1!
1+
b101 3
b10 5
b1010 7
b1011 4
b0 6
b0 8
b110 4
b0 1
b1 1
b1 &
#920000
0!
0+
#925000
1!
1+
b110 3
b0 5
b0 7
b1011 4
b111 4
b0 1
b1 1
#930000
0!
0+
#935000
1!
1+
b111 3
b1011 4
b0 1
b0 &
#940000
0!
0+
#945000
1!
1+
b1011 3
#950000
0!
0+
#955000
1!
1+
#960000
0!
0+
#965000
1!
1+
#970000
0!
0+
#975000
1!
1+
#980000
0!
0+
#985000
1!
1+
#990000
0!
0+
#995000
1!
1+
#1000000
0!
0+
#1005000
1!
1+
#1010000
0!
0+
#1015000
1!
1+
#1020000
0!
0+
#1025000
1!
1+
#1030000
0!
0+
#1035000
1!
1+
#1040000
0!
0+
#1045000
1!
1+
#1050000
0!
0+
#1055000
1!
1+
#1060000
0!
0+
#1065000
1!
1+
#1070000
0!
0+
#1075000
1!
1+
#1080000
0!
0+
#1085000
1!
1+
#1090000
0!
0+
#1095000
1!
1+
#1100000
b100 *
1#
1$
1%
0!
1.
1-
1/
0+
b0 4
#1105000
1!
1+
b0 3
b1011 4
b1 8
b0 4
b10 0
b10 '
#1110000
0!
0+
#1115000
1!
1+
b1 7
b1011 4
b0 8
b10 8
b0 4
#1120000
0!
0+
#1125000
1!
1+
b10 7
b1011 4
b0 8
b11 8
b0 4
#1130000
0!
0+
#1135000
1!
1+
b11 7
b1011 4
b0 8
b100 8
b0 4
#1140000
0!
0+
#1145000
1!
1+
b100 7
b1011 4
b0 8
b101 8
b0 4
#1150000
0!
0+
#1155000
1!
1+
b101 7
b1011 4
b0 8
b110 8
b0 4
#1160000
0!
0+
#1165000
1!
1+
b110 7
b1011 4
b0 8
b111 8
b0 4
#1170000
0!
0+
#1175000
1!
1+
b111 7
b1011 4
b0 8
b1000 8
b0 4
#1180000
0!
0+
#1185000
1!
1+
b1000 7
b1011 4
b0 8
b1001 8
b0 4
#1190000
0!
0+
#1195000
1!
1+
b1001 7
b1011 4
b0 8
b1010 8
b1 4
#1200000
0!
0+
#1205000
1!
1+
b1 3
b1010 7
b1011 4
b0 8
b10 4
b0 0
b1 0
b1 '
#1210000
0!
0+
#1215000
1!
1+
b10 3
b0 7
b1011 4
b11 4
b0 0
b1 0
#1220000
0!
0+
#1225000
1!
1+
b11 3
b1011 4
b100 4
b0 0
b0 '
#1230000
0!
0+
#1235000
1!
1+
b100 3
b1011 4
b1 8
b100 4
b10 1
b10 &
#1240000
0!
0+
#1245000
1!
1+
b1 7
b1011 4
b0 8
b10 8
b100 4
#1250000
0!
0+
#1255000
1!
1+
b10 7
b1011 4
b0 8
b11 8
b100 4
#1260000
0!
0+
#1265000
1!
1+
b11 7
b1011 4
b0 8
b100 8
b100 4
#1270000
0!
0+
#1275000
1!
1+
b100 7
b1011 4
b0 8
b101 8
b100 4
#1280000
0!
0+
#1285000
1!
1+
b101 7
b1011 4
b0 8
b110 8
b100 4
#1290000
0!
0+
#1295000
1!
1+
b110 7
b1011 4
b0 8
b111 8
b100 4
#1300000
0!
0+
#1305000
1!
1+
b111 7
b1011 4
b0 8
b1000 8
b100 4
#1310000
0!
0+
#1315000
1!
1+
b1000 7
b1011 4
b0 8
b1001 8
b100 4
#1320000
0!
0+
#1325000
1!
1+
b1001 7
b1011 4
b0 8
b1010 8
b101 4
#1330000
0!
0+
#1335000
1!
1+
b101 3
b1010 7
b1011 4
b0 8
b110 4
b0 1
b1 1
b1 &
#1340000
0!
0+
#1345000
1!
1+
b110 3
b0 7
b1011 4
b111 4
b0 1
b1 1
#1350000
0!
0+
#1355000
1!
1+
b111 3
b1011 4
b1000 4
b0 1
b0 &
#1360000
0!
0+
#1365000
1!
1+
b1000 3
b1011 4
b1 8
b1000 4
b10 2
b10 (
#1370000
0!
0+
#1375000
1!
1+
b1 7
b1011 4
b0 8
b10 8
b1000 4
#1380000
0!
0+
#1385000
1!
1+
b10 7
b1011 4
b0 8
b11 8
b1000 4
#1390000
0!
0+
#1395000
1!
1+
b11 7
b1011 4
b0 8
b100 8
b1000 4
#1400000
0!
0+
#1405000
1!
1+
b100 7
b1011 4
b0 8
b101 8
b1000 4
#1410000
0!
0+
#1415000
1!
1+
b101 7
b1011 4
b0 8
b110 8
b1000 4
#1420000
0!
0+
#1425000
1!
1+
b110 7
b1011 4
b0 8
b111 8
b1000 4
#1430000
0!
0+
#1435000
1!
1+
b111 7
b1011 4
b0 8
b1000 8
b1000 4
#1440000
0!
0+
#1445000
1!
1+
b1000 7
b1011 4
b0 8
b1001 8
b1000 4
#1450000
0!
0+
#1455000
1!
1+
b1001 7
b1011 4
b0 8
b1010 8
b1001 4
#1460000
0!
0+
#1465000
1!
1+
b1001 3
b1010 7
b1011 4
b0 8
b1010 4
b0 2
b1 2
b1 (
#1470000
0!
0+
#1475000
1!
1+
b1010 3
b0 7
b1011 4
b0 2
b1 2
#1480000
0!
0+
#1485000
1!
1+
b1011 3
b0 4
b0 2
b0 (
#1490000
0!
0+
#1495000
1!
1+
b0 3
b1011 4
b1 8
b0 4
b10 0
b10 '
#1500000
0!
0+
#1505000
1!
1+
b1 7
b1011 4
b0 8
b10 8
b0 4
#1510000
0!
0+
#1515000
1!
1+
b10 7
b1011 4
b0 8
b11 8
b0 4
#1520000
0!
0+
#1525000
1!
1+
b11 7
b1011 4
b0 8
b100 8
b0 4
#1530000
0!
0+
#1535000
1!
1+
b100 7
b1011 4
b0 8
b101 8
b0 4
#1540000
0!
0+
#1545000
1!
1+
b101 7
b1011 4
b0 8
b110 8
b0 4
#1550000
0!
0+
#1555000
1!
1+
b110 7
b1011 4
b0 8
b111 8
b0 4
#1560000
0!
0+
#1565000
1!
1+
b111 7
b1011 4
b0 8
b1000 8
b0 4
#1570000
0!
0+
#1575000
1!
1+
b1000 7
b1011 4
b0 8
b1001 8
b0 4
#1580000
0!
0+
#1585000
1!
1+
b1001 7
b1011 4
b0 8
b1010 8
b1 4
#1590000
0!
0+
#1595000
1!
1+
b1 3
b1010 7
b1011 4
b0 8
b10 4
b0 0
b1 0
b1 '
#1600000
0!
0+
#1605000
1!
1+
b10 3
b0 7
b1011 4
b11 4
b0 0
b1 0
#1610000
0!
0+
#1615000
1!
1+
b11 3
b1011 4
b100 4
b0 0
b0 '
#1620000
0!
0+
#1625000
1!
1+
b100 3
b1011 4
b1 8
b100 4
b10 1
b10 &
#1630000
0!
0+
#1635000
1!
1+
b1 7
b1011 4
b0 8
b10 8
b100 4
#1640000
0!
0+
#1645000
1!
1+
b10 7
b1011 4
b0 8
b11 8
b100 4
#1650000
0!
0+
#1655000
1!
1+
b11 7
b1011 4
b0 8
b100 8
b100 4
#1660000
0!
0+
#1665000
1!
1+
b100 7
b1011 4
b0 8
b101 8
b100 4
#1670000
0!
0+
#1675000
1!
1+
b101 7
b1011 4
b0 8
b110 8
b100 4
#1680000
0!
0+
#1685000
1!
1+
b110 7
b1011 4
b0 8
b111 8
b100 4
#1690000
0!
0+
#1695000
1!
1+
b111 7
b1011 4
b0 8
b1000 8
b100 4
#1700000
0!
0+
#1705000
1!
1+
b1000 7
b1011 4
b0 8
b1001 8
b100 4
#1710000
0!
0+
#1715000
1!
1+
b1001 7
b1011 4
b0 8
b1010 8
b101 4
#1720000
0!
0+
#1725000
1!
1+
b101 3
b1010 7
b1011 4
b0 8
b110 4
b0 1
b1 1
b1 &
#1730000
0!
0+
#1735000
1!
1+
b110 3
b0 7
b1011 4
b111 4
b0 1
b1 1
#1740000
0!
0+
#1745000
1!
1+
b111 3
b1011 4
b1000 4
b0 1
b0 &
#1750000
0!
0+
#1755000
1!
1+
b1000 3
b1011 4
b1 8
b1000 4
b10 2
b10 (
#1760000
0!
0+
#1765000
1!
1+
b1 7
b1011 4
b0 8
b10 8
b1000 4
#1770000
0!
0+
#1775000
1!
1+
b10 7
b1011 4
b0 8
b11 8
b1000 4
#1780000
0!
0+
#1785000
1!
1+
b11 7
b1011 4
b0 8
b100 8
b1000 4
#1790000
0!
0+
#1795000
1!
1+
b100 7
b1011 4
b0 8
b101 8
b1000 4
#1800000
0!
0+
#1805000
1!
1+
b101 7
b1011 4
b0 8
b110 8
b1000 4
#1810000
0!
0+
#1815000
1!
1+
b110 7
b1011 4
b0 8
b111 8
b1000 4
#1820000
0!
0+
#1825000
1!
1+
b111 7
b1011 4
b0 8
b1000 8
b1000 4
#1830000
0!
0+
#1835000
1!
1+
b1000 7
b1011 4
b0 8
b1001 8
b1000 4
#1840000
0!
0+
#1845000
1!
1+
b1001 7
b1011 4
b0 8
b1010 8
b1001 4
#1850000
0!
0+
#1855000
1!
1+
b1001 3
b1010 7
b1011 4
b0 8
b1010 4
b0 2
b1 2
b1 (
#1860000
0!
0+
#1865000
1!
1+
b1010 3
b0 7
b1011 4
b0 2
b1 2
#1870000
0!
0+
#1875000
1!
1+
b1011 3
b0 4
b0 2
b0 (
#1880000
0!
0+
#1885000
1!
1+
b0 3
b1011 4
b1 8
b0 4
b10 0
b10 '
#1890000
0!
0+
#1895000
1!
1+
b1 7
b1011 4
b0 8
b10 8
b0 4
#1900000
0!
0+
#1905000
1!
1+
b10 7
b1011 4
b0 8
b11 8
b0 4
#1910000
0!
0+
#1915000
1!
1+
b11 7
b1011 4
b0 8
b100 8
b0 4
#1920000
0!
0+
#1925000
1!
1+
b100 7
b1011 4
b0 8
b101 8
b0 4
#1930000
0!
0+
#1935000
1!
1+
b101 7
b1011 4
b0 8
b110 8
b0 4
#1940000
0!
0+
#1945000
1!
1+
b110 7
b1011 4
b0 8
b111 8
b0 4
#1950000
0!
0+
#1955000
1!
1+
b111 7
b1011 4
b0 8
b1000 8
b0 4
#1960000
0!
0+
#1965000
1!
1+
b1000 7
b1011 4
b0 8
b1001 8
b0 4
#1970000
0!
0+
#1975000
1!
1+
b1001 7
b1011 4
b0 8
b1010 8
b1 4
#1980000
0!
0+
#1985000
1!
1+
b1 3
b1010 7
b1011 4
b0 8
b10 4
b0 0
b1 0
b1 '
#1990000
0!
0+
#1995000
1!
1+
b10 3
b0 7
b1011 4
b11 4
b0 0
b1 0
#2000000
0!
0+
#2005000
1!
1+
b11 3
b1011 4
b100 4
b0 0
b0 '
#2010000
0!
0+
#2015000
1!
1+
b100 3
b1011 4
b1 8
b100 4
b10 1
b10 &
#2020000
0!
0+
#2025000
1!
1+
b1 7
b1011 4
b0 8
b10 8
b100 4
#2030000
0!
0+
#2035000
1!
1+
b10 7
b1011 4
b0 8
b11 8
b100 4
#2040000
0!
0+
#2045000
1!
1+
b11 7
b1011 4
b0 8
b100 8
b100 4
#2050000
0!
0+
#2055000
1!
1+
b100 7
b1011 4
b0 8
b101 8
b100 4
#2060000
0!
0+
#2065000
1!
1+
b101 7
b1011 4
b0 8
b110 8
b100 4
#2070000
0!
0+
#2075000
1!
1+
b110 7
b1011 4
b0 8
b111 8
b100 4
#2080000
0!
0+
#2085000
1!
1+
b111 7
b1011 4
b0 8
b1000 8
b100 4
#2090000
0!
0+
#2095000
1!
1+
b1000 7
b1011 4
b0 8
b1001 8
b100 4
#2100000
0#
0!
0.
0+
b1011 4
b0 8
b1 6
b1001 8
b100 4
#2105000
1!
1+
b1 5
b1001 7
b1011 4
b0 6
b0 8
b10 6
b1010 8
b101 4
#2110000
0!
0+
#2115000
1!
1+
b101 3
b10 5
b1010 7
b1011 4
b0 6
b0 8
b110 4
b0 1
b1 1
b1 &
#2120000
0!
0+
#2125000
1!
1+
b110 3
b0 5
b0 7
b1011 4
b111 4
b0 1
b1 1
#2130000
0!
0+
#2135000
1!
1+
b111 3
b1011 4
b1000 4
b0 1
b0 &
#2140000
0!
0+
#2145000
1!
1+
b1000 3
b1011 4
b1 8
b1000 4
b10 2
b10 (
#2150000
0!
0+
#2155000
1!
1+
b1 7
b1011 4
b0 8
b10 8
b1000 4
#2160000
0!
0+
#2165000
1!
1+
b10 7
b1011 4
b0 8
b11 8
b1000 4
#2170000
0!
0+
#2175000
1!
1+
b11 7
b1011 4
b0 8
b100 8
b1000 4
#2180000
0!
0+
#2185000
1!
1+
b100 7
b1011 4
b0 8
b101 8
b1000 4
#2190000
0!
0+
#2195000
1!
1+
b101 7
b1011 4
b0 8
b110 8
b1000 4
#2200000
0!
0+
#2205000
1!
1+
b110 7
b1011 4
b0 8
b111 8
b1000 4
#2210000
0!
0+
#2215000
1!
1+
b111 7
b1011 4
b0 8
b1000 8
b1000 4
#2220000
0!
0+
#2225000
1!
1+
b1000 7
b1011 4
b0 8
b1001 8
b1000 4
#2230000
0!
0+
#2235000
1!
1+
b1001 7
b1011 4
b0 8
b1010 8
b1001 4
#2240000
0!
0+
#2245000
1!
1+
b1001 3
b1010 7
b1011 4
b0 8
b1010 4
b0 2
b1 2
b1 (
#2250000
0!
0+
#2255000
1!
1+
b1010 3
b0 7
b1011 4
b0 2
b1 2
#2260000
0!
0+
#2265000
1!
1+
b1011 3
b0 4
b0 2
b0 (
#2270000
0!
0+
#2275000
1!
1+
b0 3
b1011 4
b1 8
b0 4
b10 0
b10 '
#2280000
0!
0+
#2285000
1!
1+
b1 7
b1011 4
b0 8
b10 8
b0 4
#2290000
0!
0+
#2295000
1!
1+
b10 7
b1011 4
b0 8
b11 8
b0 4
#2300000
0$
0%
0!
0-
0/
0+
b1011 4
b0 8
b1 6
b11 8
b0 4
